README.md
setup.py
PyEMEBSDDI_wrapper/PyEMEBSDDI.py
PyEMEBSDDI_wrapper/__init__.py
PyEMEBSDDI_wrapper.egg-info/PKG-INFO
PyEMEBSDDI_wrapper.egg-info/SOURCES.txt
PyEMEBSDDI_wrapper.egg-info/dependency_links.txt
PyEMEBSDDI_wrapper.egg-info/requires.txt
PyEMEBSDDI_wrapper.egg-info/top_level.txt
PyEMEBSDDI_wrapper/utils/__init__.py
PyEMEBSDDI_wrapper/utils/eu2qu.py
PyEMEBSDDI_wrapper/utils/imgprocess.py
PyEMEBSDDI_wrapper/utils/qu2eu.py