Metadata-Version: 2.1
Name: PyEMEBSDDI-wrapper
Version: 1.0
Summary: Python high level wrapper for PyEMEBSDDI under EMsoft
Home-page: https://github.com/Darkhunter9/PyEMEBSDDI_wrapper
Author: Zihao Ding
Author-email: ding@cmu.edu
License: UNKNOWN
Project-URL: Bug Reports, https://github.com/Darkhunter9/PyEMEBSDDI_wrapper/issues
Project-URL: Funding, http://vbff.materials.cmu.edu/EMsoft/
Project-URL: Source, https://github.com/Darkhunter9/PyEMEBSDDI_wrapper
Platform: UNKNOWN
Classifier: Development Status :: 3 - Alpha
Classifier: Topic :: Scientific/Engineering :: Physics
Classifier: License :: OSI Approved :: BSD License
Classifier: Programming Language :: Python :: 3.7
Requires-Python: >=3.7
